{"about_button.md":"fa327f71","about_status.md":"336dc1ed","about_story.md":"c6e29cfe","about_video.md":"688a062f","app_access.md":"0d47d3f2","app_integration.md":"91c52ac9","app_items.md":"3aa3f6e0","app_marketplace.md":"eaae68d8","app_provider.md":"9b412777","app_sentences.md":"f0a7a3c3","app_start.md":"9fdc721c","index.md":"4767d959","news_software-streaming.md":"cc631d66","offer_pricing.md":"7070985e","report_1.md":"9ba643a9","report_index.md":"2a4de438","user_contact.md":"7b868b0f","user_contact1.md":"f2dc8f40","user_index.md":"cbf76d88","user_investor.md":"cd4fe22a","user_markdown.md":"b5822825","user_newsletter.md":"f662b79d","user_partnership.md":"029bbc1b","user_problem.md":"b44e039a","user_registration.md":"7d0cbc16","user_survey.md":"e2e63576"}
